soda/__init__.py
soda/config_mod.py
soda/custom_tags.py
soda/paths.py
soda/point.py
soda/py.typed
soda/tags.py
soda/utils.py
soda/xml_parse.py
soda_svg-2.0.3.dist-info/LICENSE
soda_svg-2.0.3.dist-info/METADATA
soda_svg-2.0.3.dist-info/WHEEL
soda_svg-2.0.3.dist-info/RECORD
