Metadata-Version: 2.1
Name: soda-svg
Version: 2.0.3
Summary: Fast SVG generation tool
Home-page: https://github.com/evtn/soda
License: MIT
Keywords: soda,svg,xml
Author: Dmitry Gritsenko
Author-email: soda@evtn.ru
Requires-Python: >=3.8,<3.13
Classifier: License :: OSI Approved :: MIT License
Classifier: Programming Language :: Python :: 3
Classifier: Programming Language :: Python :: 3.8
Classifier: Programming Language :: Python :: 3.9
Classifier: Programming Language :: Python :: 3.10
Classifier: Programming Language :: Python :: 3.11
Classifier: Programming Language :: Python :: 3.12
Requires-Dist: lxml (>=5.2.1,<6.0.0)
Requires-Dist: types-lxml (>=2024.4.14,<2025.0.0)
Requires-Dist: wordstreamer (>=0.1.3,<0.2.0)
Project-URL: Repository, https://github.com/evtn/soda
